cloud_sql/__init__.py
cloud_sql/cloud_sql_proxy.py
cloud_sql/commandline.py
cloud_sql/config.py
cloud_sql/gcp.py
cloud_sql/instance_manager.py
cloud_sql/instances.py
cloud_sql/persistence.py
cloud_sql/running_instances.py
cloud_sql_instance_manager-0.2.9.dist-info/licenses/LICENSE
cloud_sql_instance_manager-0.2.9.dist-info/METADATA
cloud_sql_instance_manager-0.2.9.dist-info/WHEEL
cloud_sql_instance_manager-0.2.9.dist-info/entry_points.txt
cloud_sql_instance_manager-0.2.9.dist-info/top_level.txt
cloud_sql_instance_manager-0.2.9.dist-info/RECORD
