Metadata-Version: 2.4
Name: cloud_sql_instance_manager
Version: 0.2.9
Summary: Manages cloud_sql_proxy connections, allocating fixed ports and allowing control over starting and stopping
Home-page: https://github.com/zoe-j-m/cloud_sql_instance_manager
Author: Zoë Mackay
Author-email: zoe.mackay@ovo.com
Classifier: Programming Language :: Python :: 3
Classifier: License :: OSI Approved :: Apache Software License
Classifier: Operating System :: OS Independent
Requires-Python: >=3.8
License-File: LICENSE
Requires-Dist: jsonpickle
Requires-Dist: psutil
Requires-Dist: google-api-python-client
Requires-Dist: argparse
Dynamic: license-file
